clearcoreai/__init__.py
clearcoreai-0.0.1.dist-info/LICENSE
clearcoreai-0.0.1.dist-info/METADATA
clearcoreai-0.0.1.dist-info/WHEEL
clearcoreai-0.0.1.dist-info/top_level.txt
clearcoreai-0.0.1.dist-info/RECORD
