Metadata-Version: 2.1
Name: clearcoreai
Version: 0.0.1
Summary: ClearCoreAI - Transparent and robust orchestration of modular AI agents
Home-page: https://github.com/ClearCoreAI/clearcoreai
Author: Olivier Hays
Author-email: olivier@clearcore.ai
License: Apache License 2.0
License-File: LICENSE
